[
  {
    "title": "In Situ Constructed \u201cPoly\u2010Ionic Bridges\u201d Promoting Performances of All\u2010Solid\u2010State Lithium\u2010Sulfur Batteries",
    "journal": "Advanced Energy Materials",
    "url": "https://advanced.onlinelibrary.wiley.com/doi/10.1002/aenm.70792?af=R",
    "doi": "10.1002/aenm.70792",
    "authors": [
      "Kang Du, \nYimin Xuan, \nDi Li, \nHong Li"
    ],
    "abstract": "Volume 16, Issue 17, 6 May 2026.",
    "published": "2026-05-06T09:56:41+00:00",
    "score": 7.3
  },
  {
    "title": "Synergistic Interface Engineering of Heterojunction and Oxygen Vacancies in Multiphase Cobalt Oxide/Graphene Composite Host for High\u2010Performance Lithium\u2013Sulfur Batteries",
    "journal": "Advanced Energy Materials",
    "url": "https://advanced.onlinelibrary.wiley.com/doi/10.1002/aenm.202506549?af=R",
    "doi": "10.1002/aenm.202506549",
    "authors": [
      "Liang Liu, \nHong Cui, \nJiacheng Shen, \nXin Wang, \nLanling Zhao, \nYouzhong Dong, \nQinghua Fan, \nJiantie Xu"
    ],
    "abstract": "Volume 16, Issue 17, 6 May 2026.",
    "published": "2026-05-06T09:56:41+00:00",
    "score": 4.4
  },
  {
    "title": "A Dual\u2010Salt/Dual\u2010Polymer Quasi\u2010<b>Solid Electrolyte</b> for High\u2010Performance <b>Lithium</b>\u2013Oxygen Batteries",
    "journal": "Advanced Functional Materials",
    "url": "https://advanced.onlinelibrary.wiley.com/doi/10.1002/adfm.75735?af=R",
    "doi": "10.1002/adfm.75735",
    "authors": [
      "Yongji Xia, \nSicheng Fan, \nHongfei Zheng, \nShiyu Zhang, \nXinchao Hu, \nRenjie Xu, \nYingpeng Du, \nJian Yan, \nSheng Lin, \nJiajia Han, \nZhaoju Yu, \nDong\u2010Liang Peng, \nGuanghui Yue"
    ],
    "abstract": "EarlyView.",
    "published": "2026-05-06T13:05:25+00:00",
    "score": 4.4
  },
  {
    "title": "In situ synchrotron X-ray computed tomography of structural evolution in silicon anodes for all-solid-state batteries",
    "journal": "Journal of Power Sources",
    "url": "https://www.sciencedirect.com/science/article/pii/S0378775326010529?dgcid=rss_sd_all",
    "doi": null,
    "authors": [],
    "abstract": "Publication date: 30 July 2026 Source: , Volume 681 Author(s): Kentaro Takase, Naoki Koshitani, Aiko Kanazawa, Nobuyuki Nagaoka, Yusuke Morino",
    "published": null,
    "score": 3.9
  },
  {
    "title": "[ASAP] Local Thermal Strain Regulated <b>Solid Electrolyte</b> <b>Interphase</b> with Advanced High-Temperature Tolerance",
    "journal": "Journal of the American Chemical Society",
    "url": "http://dx.doi.org/10.1021/jacs.6c02582",
    "doi": "10.1021/jacs.6c02582",
    "authors": [
      "Gaobo Chang, Hanqing Zhao, Boyan Cui, Hailong Zhang, Shouyao Li, Lipeng Zhang, Zhong Li, and Jieshan Qiu"
    ],
    "abstract": "DOI: 10.1021/jacs.6c02582",
    "published": "2026-05-06T19:50:11+00:00",
    "score": 3.7
  },
  {
    "title": "Composite Polymer Electrolyte With Functional 2D GCN for Improved Na\u2010Ion Transport and Na Metal Compatibility of All\u2010Solid\u2010State Sodium\u2010Ion Batteries",
    "journal": "Advanced Functional Materials",
    "url": "https://advanced.onlinelibrary.wiley.com/doi/10.1002/adfm.75729?af=R",
    "doi": "10.1002/adfm.75729",
    "authors": [
      "Sudharshan Vasudevan, \nSushmita Dwivedi, \nLi Jicheng, \nKarthick Babu Morekonda Ganesh Babu, \nPalani Balaya"
    ],
    "abstract": "EarlyView.",
    "published": "2026-05-06T13:07:14+00:00",
    "score": 3.7
  },
  {
    "title": "A 50 \u00b5m\u2010Thick Fiber\u2010Reinforced Fluorinated Polymer Plastic Crystal Electrolyte Enabling High <b>Ionic Conductivity</b> and Voltage Stability for Advanced Solid\u2010State <b>Sodium</b> Batteries",
    "journal": "Advanced Energy Materials",
    "url": "https://advanced.onlinelibrary.wiley.com/doi/10.1002/aenm.71026?af=R",
    "doi": "10.1002/aenm.71026",
    "authors": [
      "Tingfeng Deng, \nRui Wang, \nYa You, \nHongwei Kang, \nXiaodong Wu, \nLing Liu, \nWenjuan Zhang, \nHongbao Li, \nLonghai Zhang, \nChaofeng Zhang"
    ],
    "abstract": "EarlyView.",
    "published": "2026-05-06T09:01:54+00:00",
    "score": 3.3
  },
  {
    "title": "A parametric analysis of <b>thermal runaway</b> and its mitigation in large-scale lithium-ion battery storage scenarios",
    "journal": "Journal of Energy Storage",
    "url": "https://www.sciencedirect.com/science/article/pii/S2352152X26020736?dgcid=rss_sd_all",
    "doi": null,
    "authors": [],
    "abstract": "Publication date: 30 July 2026 Source: , Volume 167 Author(s): Muhammad Mehdi Abbas, Byoungchul Kwon, Vinay Premnath, Judith Jeevarajan, Ankur Jain",
    "published": null,
    "score": 3.2
  },
  {
    "title": "Multi-fidelity surrogate modeling for lithium-ion battery pack <b>thermal runaway</b> propagation considering propagation occurrence in adaptive sampling",
    "journal": "Journal of Energy Storage",
    "url": "https://www.sciencedirect.com/science/article/pii/S2352152X26021122?dgcid=rss_sd_all",
    "doi": null,
    "authors": [],
    "abstract": "Publication date: 30 July 2026 Source: , Volume 167 Author(s): Yiyue Jiang, Jiayi Zhao, Zheng Liu, Pingfeng Wang",
    "published": null,
    "score": 3.2
  },
  {
    "title": "A 1,2-dimethoxyethane-based high-concentration weakly-solvated electrolyte enabling high-voltage high-safety lithium-ion cells",
    "journal": "Journal of Power Sources",
    "url": "https://www.sciencedirect.com/science/article/pii/S0378775326010505?dgcid=rss_sd_all",
    "doi": null,
    "authors": [],
    "abstract": "Publication date: 30 July 2026 Source: , Volume 681 Author(s): Dongxu Ouyang, Jun Guan, Xiaotian Wan, Hao Ding, Chunyang Miao, Zhirong Wang",
    "published": null,
    "score": 3.1
  },
  {
    "title": "First-principles computational design of a novel two-dimensional SHfSiN<sub>2</sub> anode for <b>lithium</b>, <b>sodium</b>, and multivalent metal ion batteries",
    "journal": "Journal of Power Sources",
    "url": "https://www.sciencedirect.com/science/article/pii/S037877532601027X?dgcid=rss_sd_all",
    "doi": null,
    "authors": [],
    "abstract": "Publication date: 30 July 2026 Source: , Volume 681 Author(s): Sheraz Ahmad, Nouari Saheb, Arifur Rahman, Irina Piyanzina",
    "published": null,
    "score": 3.1
  },
  {
    "title": "Malleable textured Li for practical <b>lithium</b> metal batteries over 8,902 W kg<sup>\u22121</sup>",
    "journal": "Joule",
    "url": "https://www.sciencedirect.com/science/article/pii/S2542435126001546?dgcid=rss_sd_all",
    "doi": null,
    "authors": [],
    "abstract": "Publication date: Available online 6 May 2026 Source:  Author(s): Menglu Li, Hanwen An, Haiqing Lv, Linxue Zhang, Jiaxuan Liu, Shengkai Mo, Dakang Peng, Qingsong Liu, Ge Zhu, Biao Deng, Jiajun Wang",
    "published": null,
    "score": 3.0
  },
  {
    "title": "[ASAP] Latticed Cd2+ Doping for Enhanced Ionic Transport in Li2ZrCl6 Solid-State Electrolytes toward High-Performance All-Solid-State Batteries",
    "journal": "ACS Applied Materials & Interfaces",
    "url": "http://dx.doi.org/10.1021/acsami.6c03952",
    "doi": "10.1021/acsami.6c03952",
    "authors": [
      "Chao Wu, Zhen Wang, Jiawu Cui, Qi Ling, Xianwei Wang, Zexun Tang, Chengyong Shu, Kang Yang, Yuping Wu, and Wei Tang"
    ],
    "abstract": "ACS Applied Materials &amp; Interfaces DOI: 10.1021/acsami.6c03952",
    "published": "2026-05-07T08:39:44+00:00",
    "score": 3.0
  },
  {
    "title": "In-situ activation of sulfur during electropolymerization of aniline for high-performance binder-free sulfur-polyaniline composite cathodes in <b>lithium-sulfur</b> batteries",
    "journal": "Electrochimica Acta",
    "url": "https://www.sciencedirect.com/science/article/pii/S0013468626008236?dgcid=rss_sd_all",
    "doi": null,
    "authors": [],
    "abstract": "Publication date: 10 September 2026 Source: , Volume 570 Author(s): Ying Rong, Shihua Chen, Shujie Li, Qi Wang, Xuwei Zhang, Lan Yuan, Yang Gui, Baoan Fan, Fen Guo",
    "published": null,
    "score": 3.0
  },
  {
    "title": "Enhanced interfacial stability and electrochemical performance via cathode-adhesion-enhanced coatings for all-solid-state batteries",
    "journal": "Energy Storage Materials",
    "url": "https://www.sciencedirect.com/science/article/pii/S2405829726003004?dgcid=rss_sd_all",
    "doi": null,
    "authors": [],
    "abstract": "Publication date: June 2026 Source: , Volume 89 Author(s): Junseong Kim, Hoseok Lee, Taegyu Kim, Eunyoung Ryu, Imsul Seo, Ju Yeong Seong, Chungbum Lim, Jongsoon Kim",
    "published": null,
    "score": 3.0
  },
  {
    "title": "Design of Cross\u2010linked Polymer Deep Eutectic Electrolytes for High\u2010voltage Long\u2010Cycle <b>Lithium</b> Metal Batteries via Solvation Regulation of Polymerizable Deep Eutectic Solvent Monomers",
    "journal": "Advanced Energy Materials",
    "url": "https://advanced.onlinelibrary.wiley.com/doi/10.1002/aenm.202505218?af=R",
    "doi": "10.1002/aenm.202505218",
    "authors": [
      "Rui Huang, \nLirong Xiang, \nFuping Bian, \nJunhao Cheng, \nZihan Jiang, \nJiali Zhao, \nMinghui He"
    ],
    "abstract": "Volume 16, Issue 17, 6 May 2026.",
    "published": "2026-05-06T09:56:41+00:00",
    "score": 2.9
  },
  {
    "title": "Dynamic Cross\u2010Linking of Organosulfur and Organoselenium in a Biphasic Cathode for Balanced High\u2010Performance <b>Lithium</b> Batteries",
    "journal": "Advanced Energy Materials",
    "url": "https://advanced.onlinelibrary.wiley.com/doi/10.1002/aenm.71037?af=R",
    "doi": "10.1002/aenm.71037",
    "authors": [
      "Zhuoyan Qu, \nRu Xiao, \nTong Yu, \nXiaoyin Zhang, \nZhenhua Sun, \nFeng Li"
    ],
    "abstract": "EarlyView.",
    "published": "2026-05-06T09:12:25+00:00",
    "score": 2.9
  },
  {
    "title": "A Quantitative <b>Lithium</b> Inventory Framework for Anode\u2010Free <b>Lithium</b> Metal Batteries",
    "journal": "Advanced Energy Materials",
    "url": "https://advanced.onlinelibrary.wiley.com/doi/10.1002/aenm.71028?af=R",
    "doi": "10.1002/aenm.71028",
    "authors": [
      "Wurigumula Bao, \nAlex Liu, \nThomas S. Marchese, \nYuanlong Bill Zheng, \nWeikang Li, \nDhevathi Rajan Rajagopalan Kannan, \nVallabha Rao Rikka, \nVinay Premnath, \nJudith Jeevarajan, \nYing Shirley Meng"
    ],
    "abstract": "EarlyView.",
    "published": "2026-05-06T08:57:49+00:00",
    "score": 2.9
  },
  {
    "title": "Mechanical-electrical decoupling failure of pouch lithium-ion batteries under mechanical abuse: Role of indenter type",
    "journal": "Journal of Energy Storage",
    "url": "https://www.sciencedirect.com/science/article/pii/S2352152X26021730?dgcid=rss_sd_all",
    "doi": null,
    "authors": [],
    "abstract": "Publication date: 30 July 2026 Source: , Volume 167 Author(s): Guofeng Liu, Can Wang, Renjie Wang, Quanqing Yu, Jiahuan Lu",
    "published": null,
    "score": 2.5
  },
  {
    "title": "Modelling thermal behavior of carbon-sulphur composite cathode in lithium-sulphur batteries",
    "journal": "Journal of Energy Storage",
    "url": "https://www.sciencedirect.com/science/article/pii/S2352152X26022656?dgcid=rss_sd_all",
    "doi": null,
    "authors": [],
    "abstract": "Publication date: 30 July 2026 Source: , Volume 167 Author(s): Chandan Prasad, Abhishek Sarkar",
    "published": null,
    "score": 2.5
  },
  {
    "title": "Towards trustworthy lithium-ion battery remaining useful life prediction with uncertainty quantification",
    "journal": "Journal of Energy Storage",
    "url": "https://www.sciencedirect.com/science/article/pii/S2352152X26020724?dgcid=rss_sd_all",
    "doi": null,
    "authors": [],
    "abstract": "Publication date: 30 July 2026 Source: , Volume 167 Author(s): Zhibin Zhao, Mingqi Feng, Qiuyu Yu, Hongming Yuan, Fujin Wang, Zhi Zhai",
    "published": null,
    "score": 2.5
  },
  {
    "title": "DMC-rich, low-EC, moderately concentrated electrolytes for lithium-ion batteries: Roles of solvent composition and salt concentration",
    "journal": "Journal of Power Sources",
    "url": "https://www.sciencedirect.com/science/article/pii/S0378775326009924?dgcid=rss_sd_all",
    "doi": null,
    "authors": [],
    "abstract": "Publication date: 30 July 2026 Source: , Volume 681 Author(s): Yuji Ide, Yanko Marinov Todorov, Masaki Deguchi, Koji Abe",
    "published": null,
    "score": 2.4
  },
  {
    "title": "Lithium-ion battery swelling characterisation using high-resolution optical fibre-based surface profiler and thermal imaging",
    "journal": "Journal of Power Sources",
    "url": "https://www.sciencedirect.com/science/article/pii/S0378775326010463?dgcid=rss_sd_all",
    "doi": null,
    "authors": [],
    "abstract": "Publication date: 30 July 2026 Source: , Volume 681 Author(s): Zhen Guo, Md Abul Kashem, Calum Briggs, Lee Oldham, Anup Barai, James Marco",
    "published": null,
    "score": 2.4
  },
  {
    "title": "Addressing Bottlenecks to Achieve High\u2010Energy Sodium\u2010Ion Cells Using Tin Anodes",
    "journal": "Advanced Energy Materials",
    "url": "https://advanced.onlinelibrary.wiley.com/doi/10.1002/aenm.202600009?af=R",
    "doi": "10.1002/aenm.202600009",
    "authors": [
      "Parth Desai, \nHarshita Lohani, \nWang Yu, \nFran\u00e7ois Ribot, \nGuillaume P. Laurent, \nJulien Bonefacino, \nHerv\u00e9 Vezin, \nDominique Foix, \nCarine Davoisne, \nBiao Zhang, \nJean\u2010Marie Tarascon, \nSathiya Mariyappan"
    ],
    "abstract": "Volume 16, Issue 17, 6 May 2026.",
    "published": "2026-05-06T09:56:41+00:00",
    "score": 2.1
  },
  {
    "title": "Synergistic Engineering of Hollow Nanospherical Structure and Closed\u2010Pore in Hard Carbons for Ultra\u2010Stable and High\u2010Utilization <b>Sodium</b> Storage",
    "journal": "Advanced Energy Materials",
    "url": "https://advanced.onlinelibrary.wiley.com/doi/10.1002/aenm.202506523?af=R",
    "doi": "10.1002/aenm.202506523",
    "authors": [
      "Jiaying Yang, \nRong Zhuang, \nKejie Wang, \nDengke Liu, \nYue Ma, \nJiangan Wang, \nHongqiang Wang, \nFei Xu"
    ],
    "abstract": "Volume 16, Issue 17, 6 May 2026.",
    "published": "2026-05-06T09:56:41+00:00",
    "score": 2.1
  },
  {
    "title": "Multiple\u2010Center Cation Ordering Mitigates Voltage Decay and Hysteresis in <b>Sodium</b> Layered Oxides",
    "journal": "Advanced Energy Materials",
    "url": "https://advanced.onlinelibrary.wiley.com/doi/10.1002/aenm.202506773?af=R",
    "doi": "10.1002/aenm.202506773",
    "authors": [
      "Yaru Guo, \nXiaohong Liu, \nXu Zhu, \nYajun Ni, \nHaojie Dong, \nShao\u2010Wen Xu, \nMengting Liu, \nPeng\u2010Fei An, \nXing Zhang, \nJing Zhang, \nYue Zhang, \nPeng\u2010Fei Wang, \nSailong Xu, \nYa\u2010Xia Yin"
    ],
    "abstract": "Volume 16, Issue 17, 6 May 2026.",
    "published": "2026-05-06T09:56:41+00:00",
    "score": 2.1
  },
  {
    "title": "[ASAP] Molecular-Scale Hybrid Strategy Synergizes Solvation Regulation and SO42\u2013-Derived Inorganic-Rich <b>SEI</b> for Zn Anodes",
    "journal": "ACS Energy Letters",
    "url": "http://dx.doi.org/10.1021/acsenergylett.6c00395",
    "doi": "10.1021/acsenergylett.6c00395",
    "authors": [
      "Jingzhu Chen, Biyao Du, Yang Xu, Peng Ying, Zhuoran Lv, Tianquan Lin, Luke Yan, Wujie Dong, Hui Bi, and Fuqiang Huang"
    ],
    "abstract": "DOI: 10.1021/acsenergylett.6c00395",
    "published": "2026-05-06T16:04:57+00:00",
    "score": 2.0
  },
  {
    "title": "One-step surface modification of O3-layered oxide for <b>sodium-ion</b> batteries with improved cycling performance",
    "journal": "Journal of Power Sources",
    "url": "https://www.sciencedirect.com/science/article/pii/S037877532601044X?dgcid=rss_sd_all",
    "doi": null,
    "authors": [],
    "abstract": "Publication date: 30 July 2026 Source: , Volume 681 Author(s): Dongrui Xie, Tengfei Song, Peter R. Slater, Mark J.H. Simmons, Emma Kendrick",
    "published": null,
    "score": 1.6
  },
  {
    "title": "Stabilizing Polyquinone Cathodes via LiPON Coating: An Interfacial Strategy for Dissolution-Resistant Lithium-Organic Batteries",
    "journal": "Electrochimica Acta",
    "url": "https://www.sciencedirect.com/science/article/pii/S0013468626009308?dgcid=rss_sd_all",
    "doi": null,
    "authors": [],
    "abstract": "Publication date: Available online 7 May 2026 Source:  Author(s): Zhen Chen, Yan Wang, Yong Chang, Xin Han, Xingxing Li, Shiyu Zhou, Faquan Yu, Minghua Zhou",
    "published": null,
    "score": 1.5
  },
  {
    "title": "Molecular engineering enhances dielectric shielding for high-performance lithium-metal batteries",
    "journal": "Energy Storage Materials",
    "url": "https://www.sciencedirect.com/science/article/pii/S2405829726003119?dgcid=rss_sd_all",
    "doi": null,
    "authors": [],
    "abstract": "Publication date: June 2026 Source: , Volume 89 Author(s): Jing Lian, Shendong Tan, Tingzheng Hou, Ziqiang Wang",
    "published": null,
    "score": 1.5
  }
]